ccvm_simulators/__init__.py
ccvm_simulators/metadata_list.py
ccvm_simulators/solution.py
ccvm_simulators/ccvmplotlib/__init__.py
ccvm_simulators/ccvmplotlib/ccvmplotlib.py
ccvm_simulators/ccvmplotlib/problem_metadata/__init__.py
ccvm_simulators/ccvmplotlib/problem_metadata/boxqp_metadata.py
ccvm_simulators/ccvmplotlib/problem_metadata/problem_metadata.py
ccvm_simulators/ccvmplotlib/problem_metadata/problem_metadata_factory.py
ccvm_simulators/ccvmplotlib/tests/__init__.py
ccvm_simulators/ccvmplotlib/tests/test_BoxQP_metadata.py
ccvm_simulators/ccvmplotlib/tests/test_ccvmplotlib.py
ccvm_simulators/ccvmplotlib/tests/test_problem_metadata.py
ccvm_simulators/ccvmplotlib/tests/test_problem_metadata_factory.py
ccvm_simulators/ccvmplotlib/utils/__init__.py
ccvm_simulators/ccvmplotlib/utils/metric.py
ccvm_simulators/ccvmplotlib/utils/mixins.py
ccvm_simulators/ccvmplotlib/utils/sampleTTSmetric.py
ccvm_simulators/ccvmplotlib/utils/utilities.py
ccvm_simulators/post_processor/__init__.py
ccvm_simulators/post_processor/adam.py
ccvm_simulators/post_processor/asgd.py
ccvm_simulators/post_processor/bfgs.py
ccvm_simulators/post_processor/box_qp_model.py
ccvm_simulators/post_processor/factory.py
ccvm_simulators/post_processor/lbfgs.py
ccvm_simulators/post_processor/post_processor.py
ccvm_simulators/post_processor/trust_constr.py
ccvm_simulators/post_processor/tests/__init__.py
ccvm_simulators/post_processor/tests/test_adam.py
ccvm_simulators/post_processor/tests/test_asgd.py
ccvm_simulators/post_processor/tests/test_bfgs.py
ccvm_simulators/post_processor/tests/test_box_qp_model.py
ccvm_simulators/post_processor/tests/test_factory.py
ccvm_simulators/post_processor/tests/test_lbfgs.py
ccvm_simulators/post_processor/tests/test_trust_constr.py
ccvm_simulators/post_processor/tests/unit_test.py
ccvm_simulators/problem_classes/__init__.py
ccvm_simulators/problem_classes/boxqp/__init__.py
ccvm_simulators/problem_classes/boxqp/problem_instance.py
ccvm_simulators-1.0.1.dist-info/LICENSE
ccvm_simulators-1.0.1.dist-info/METADATA
ccvm_simulators-1.0.1.dist-info/WHEEL
ccvm_simulators-1.0.1.dist-info/top_level.txt
ccvm_simulators-1.0.1.dist-info/RECORD
