Metadata-Version: 2.1
Name: ccvm-simulators
Version: 1.0.1
Summary: Solve continuous non-convex optimization problems with CCVM architectures and simulators
Home-page: https://github.com/1QB-Information-Technologies/ccvm
Author: 1QBit
Author-email: support@1qbit.com
License: GNU Affero General Public License v3.0
Classifier: Development Status :: 3 - Alpha
Classifier: Intended Audience :: Science/Research
Classifier: Intended Audience :: Developers
Classifier: Operating System :: MacOS
Classifier: Operating System :: POSIX :: Linux
Classifier: Programming Language :: Python :: 3.10
Classifier: Programming Language :: Python :: 3.11
License-File: LICENSE
Requires-Dist: setuptools (==66.0.0)
Requires-Dist: future (==0.18.3)
Requires-Dist: matplotlib (==3.6.3)
Requires-Dist: numpy (==1.24.1)
Requires-Dist: pandas (==1.5.2)
Requires-Dist: pytest (==7.2.0)
Requires-Dist: scipy (==1.10.0)
Requires-Dist: torch (==1.13.1)
Requires-Dist: json-stream (==1.5.2)
Requires-Dist: tqdm (==4.64.1)
Requires-Dist: xmlrunner (==1.7.7)
